[
    {
        "input": "exquisite",
        "output": "K"
    },
    {
        "input": "out",
        "output": "T"
    },
    {
        "input": "bad",
        "output": "S"
    },
    {
        "input": "inside",
        "output": "C"
    },
    {
        "input": "zany",
        "output": "A"
    },
    {
        "input": "jellyfish",
        "output": "H"
    },
    {
        "input": "you",
        "output": "Z"
    },
    {
        "input": "grateful",
        "output": "B"
    },
    {
        "input": "below",
        "output": "R"
    },
    {
        "input": "white",
        "output": "Z"
    },
    {
        "input": "microphone",
        "output": "J"
    },
    {
        "input": "tranquil",
        "output": "Q"
    },
    {
        "input": "dark",
        "output": "T"
    },
    {
        "input": "vivacious",
        "output": "B"
    },
    {
        "input": "trustworthy",
        "output": "Y"
    },
    {
        "input": "ukulele",
        "output": "J"
    },
    {
        "input": "zipper",
        "output": "S"
    },
    {
        "input": "we",
        "output": "D"
    },
    {
        "input": "raspberry",
        "output": "Y"
    },
    {
        "input": "sensitive",
        "output": "G"
    },
    {
        "input": "down",
        "output": "A"
    },
    {
        "input": "decide",
        "output": "J"
    },
    {
        "input": "nurturing",
        "output": "V"
    },
    {
        "input": "kite",
        "output": "D"
    },
    {
        "input": "ink",
        "output": "A"
    },
    {
        "input": "paper",
        "output": "D"
    },
    {
        "input": "violin",
        "output": "F"
    },
    {
        "input": "unwavering",
        "output": "L"
    },
    {
        "input": "carrot",
        "output": "F"
    },
    {
        "input": "but",
        "output": "B"
    },
    {
        "input": "talk",
        "output": "M"
    },
    {
        "input": "her",
        "output": "R"
    },
    {
        "input": "crane",
        "output": "X"
    },
    {
        "input": "crab",
        "output": "O"
    },
    {
        "input": "incense",
        "output": "J"
    },
    {
        "input": "past",
        "output": "J"
    },
    {
        "input": "resourceful",
        "output": "C"
    },
    {
        "input": "launch",
        "output": "V"
    },
    {
        "input": "near",
        "output": "Z"
    },
    {
        "input": "donkey",
        "output": "A"
    },
    {
        "input": "tennis racket",
        "output": "H"
    },
    {
        "input": "loud",
        "output": "N"
    },
    {
        "input": "envelope",
        "output": "T"
    },
    {
        "input": "peaceful",
        "output": "R"
    },
    {
        "input": "feather",
        "output": "G"
    },
    {
        "input": "gather",
        "output": "G"
    },
    {
        "input": "red",
        "output": "A"
    },
    {
        "input": "chair",
        "output": "S"
    },
    {
        "input": "which",
        "output": "F"
    },
    {
        "input": "since",
        "output": "G"
    },
    {
        "input": "create",
        "output": "G"
    },
    {
        "input": "curtain",
        "output": "C"
    },
    {
        "input": "us",
        "output": "S"
    },
    {
        "input": "toward",
        "output": "T"
    },
    {
        "input": "zealous",
        "output": "A"
    },
    {
        "input": "mellow",
        "output": "H"
    },
    {
        "input": "salamander",
        "output": "W"
    },
    {
        "input": "puzzle",
        "output": "I"
    },
    {
        "input": "knit",
        "output": "G"
    },
    {
        "input": "wristwatch",
        "output": "P"
    },
    {
        "input": "search",
        "output": "L"
    },
    {
        "input": "dolphin",
        "output": "N"
    },
    {
        "input": "brave",
        "output": "U"
    },
    {
        "input": "fierce",
        "output": "R"
    },
    {
        "input": "ocelot",
        "output": "S"
    },
    {
        "input": "notice",
        "output": "S"
    },
    {
        "input": "candle",
        "output": "P"
    },
    {
        "input": "orangutan",
        "output": "S"
    },
    {
        "input": "zoom",
        "output": "Q"
    },
    {
        "input": "papaya",
        "output": "U"
    },
    {
        "input": "destroy",
        "output": "B"
    },
    {
        "input": "fishing pole",
        "output": "F"
    },
    {
        "input": "visit",
        "output": "L"
    },
    {
        "input": "understand",
        "output": "S"
    },
    {
        "input": "calm",
        "output": "Y"
    },
    {
        "input": "hammer",
        "output": "B"
    },
    {
        "input": "hairbrush",
        "output": "S"
    },
    {
        "input": "leopard",
        "output": "S"
    },
    {
        "input": "passionate",
        "output": "A"
    },
    {
        "input": "teach",
        "output": "G"
    },
    {
        "input": "chinchilla",
        "output": "D"
    },
    {
        "input": "radiant",
        "output": "X"
    },
    {
        "input": "agreeable",
        "output": "T"
    },
    {
        "input": "pasta",
        "output": "N"
    },
    {
        "input": "perform",
        "output": "M"
    },
    {
        "input": "intuitive",
        "output": "D"
    },
    {
        "input": "remote",
        "output": "Q"
    },
    {
        "input": "adoring",
        "output": "C"
    },
    {
        "input": "worm",
        "output": "A"
    },
    {
        "input": "whimsical",
        "output": "Q"
    },
    {
        "input": "loving",
        "output": "A"
    },
    {
        "input": "judge",
        "output": "G"
    },
    {
        "input": "sloth",
        "output": "C"
    },
    {
        "input": "salmon",
        "output": "C"
    },
    {
        "input": "x-ray",
        "output": "P"
    },
    {
        "input": "small",
        "output": "P"
    },
    {
        "input": "into",
        "output": "D"
    },
    {
        "input": "volunteer",
        "output": "E"
    },
    {
        "input": "serve",
        "output": "G"
    },
    {
        "input": "wise",
        "output": "H"
    },
    {
        "input": "hornet",
        "output": "D"
    },
    {
        "input": "for",
        "output": "F"
    },
    {
        "input": "monkey",
        "output": "N"
    },
    {
        "input": "kettle",
        "output": "K"
    },
    {
        "input": "peacock",
        "output": "J"
    },
    {
        "input": "themselves",
        "output": "H"
    },
    {
        "input": "baboon",
        "output": "L"
    },
    {
        "input": "whoever",
        "output": "C"
    },
    {
        "input": "sheep",
        "output": "B"
    },
    {
        "input": "rock",
        "output": "C"
    },
    {
        "input": "update",
        "output": "V"
    },
    {
        "input": "lamp",
        "output": "T"
    },
    {
        "input": "piano",
        "output": "T"
    },
    {
        "input": "hopeful",
        "output": "T"
    },
    {
        "input": "kindred",
        "output": "M"
    },
    {
        "input": "realize",
        "output": "W"
    },
    {
        "input": "during",
        "output": "S"
    },
    {
        "input": "ibex",
        "output": "J"
    },
    {
        "input": "drum",
        "output": "T"
    },
    {
        "input": "butterfly",
        "output": "C"
    },
    {
        "input": "light",
        "output": "L"
    },
    {
        "input": "olive",
        "output": "F"
    },
    {
        "input": "manatee",
        "output": "A"
    },
    {
        "input": "plant",
        "output": "A"
    },
    {
        "input": "merge",
        "output": "L"
    },
    {
        "input": "gnu",
        "output": "M"
    },
    {
        "input": "guitar",
        "output": "R"
    },
    {
        "input": "skates",
        "output": "I"
    },
    {
        "input": "measure",
        "output": "S"
    },
    {
        "input": "pelican",
        "output": "F"
    },
    {
        "input": "idealistic",
        "output": "D"
    },
    {
        "input": "bitter",
        "output": "B"
    },
    {
        "input": "overcome",
        "output": "F"
    },
    {
        "input": "garlic",
        "output": "S"
    },
    {
        "input": "strawberry",
        "output": "O"
    },
    {
        "input": "verify",
        "output": "E"
    },
    {
        "input": "big",
        "output": "K"
    },
    {
        "input": "jackfruit",
        "output": "W"
    },
    {
        "input": "innocent",
        "output": "P"
    },
    {
        "input": "nurture",
        "output": "P"
    },
    {
        "input": "lemon",
        "output": "B"
    },
    {
        "input": "silly",
        "output": "K"
    },
    {
        "input": "participate",
        "output": "I"
    },
    {
        "input": "humble",
        "output": "J"
    },
    {
        "input": "seahorse",
        "output": "W"
    },
    {
        "input": "select",
        "output": "M"
    },
    {
        "input": "emu",
        "output": "H"
    },
    {
        "input": "thirsty",
        "output": "M"
    },
    {
        "input": "turtle",
        "output": "R"
    },
    {
        "input": "dice",
        "output": "G"
    },
    {
        "input": "gold",
        "output": "C"
    },
    {
        "input": "coconut",
        "output": "S"
    },
    {
        "input": "resolute",
        "output": "P"
    },
    {
        "input": "herself",
        "output": "S"
    },
    {
        "input": "apron",
        "output": "V"
    },
    {
        "input": "globe",
        "output": "P"
    },
    {
        "input": "boar",
        "output": "D"
    },
    {
        "input": "snake",
        "output": "L"
    },
    {
        "input": "finch",
        "output": "U"
    },
    {
        "input": "of",
        "output": "B"
    },
    {
        "input": "mustard",
        "output": "P"
    },
    {
        "input": "notebook",
        "output": "E"
    },
    {
        "input": "from",
        "output": "C"
    },
    {
        "input": "practice",
        "output": "N"
    },
    {
        "input": "buffalo",
        "output": "T"
    },
    {
        "input": "argue",
        "output": "S"
    },
    {
        "input": "unite",
        "output": "R"
    },
    {
        "input": "yield",
        "output": "U"
    },
    {
        "input": "duster",
        "output": "Z"
    },
    {
        "input": "hoop",
        "output": "R"
    },
    {
        "input": "zesty",
        "output": "H"
    },
    {
        "input": "cheetah",
        "output": "C"
    },
    {
        "input": "vibrant",
        "output": "T"
    },
    {
        "input": "uncover",
        "output": "Z"
    },
    {
        "input": "macaw",
        "output": "A"
    },
    {
        "input": "pink",
        "output": "R"
    },
    {
        "input": "among",
        "output": "P"
    },
    {
        "input": "pillow",
        "output": "H"
    },
    {
        "input": "rat",
        "output": "M"
    },
    {
        "input": "devoted",
        "output": "H"
    },
    {
        "input": "query",
        "output": "W"
    },
    {
        "input": "make",
        "output": "A"
    },
    {
        "input": "test",
        "output": "U"
    },
    {
        "input": "believe",
        "output": "M"
    },
    {
        "input": "mint",
        "output": "W"
    },
    {
        "input": "gumball",
        "output": "P"
    },
    {
        "input": "treat",
        "output": "Z"
    },
    {
        "input": "weak",
        "output": "Q"
    },
    {
        "input": "tomato",
        "output": "L"
    },
    {
        "input": "hear",
        "output": "H"
    },
    {
        "input": "unselfish",
        "output": "B"
    },
    {
        "input": "falcon",
        "output": "C"
    },
    {
        "input": "intrepid",
        "output": "A"
    },
    {
        "input": "manage",
        "output": "S"
    },
    {
        "input": "by",
        "output": "G"
    },
    {
        "input": "knowledgeable",
        "output": "D"
    },
    {
        "input": "gecko",
        "output": "R"
    },
    {
        "input": "resilient",
        "output": "Q"
    },
    {
        "input": "joyful",
        "output": "K"
    },
    {
        "input": "observant",
        "output": "K"
    },
    {
        "input": "yogurt",
        "output": "L"
    },
    {
        "input": "octopus",
        "output": "F"
    },
    {
        "input": "focus",
        "output": "S"
    },
    {
        "input": "me",
        "output": "H"
    },
    {
        "input": "warm",
        "output": "T"
    },
    {
        "input": "gazelle",
        "output": "B"
    },
    {
        "input": "plate",
        "output": "R"
    },
    {
        "input": "knot",
        "output": "P"
    },
    {
        "input": "banana",
        "output": "B"
    },
    {
        "input": "dislike",
        "output": "J"
    },
    {
        "input": "off",
        "output": "R"
    },
    {
        "input": "tangerine",
        "output": "K"
    },
    {
        "input": "laugh",
        "output": "Z"
    },
    {
        "input": "need",
        "output": "D"
    },
    {
        "input": "pomegranate",
        "output": "C"
    },
    {
        "input": "around",
        "output": "O"
    },
    {
        "input": "igloo",
        "output": "A"
    },
    {
        "input": "eager",
        "output": "E"
    },
    {
        "input": "breathe",
        "output": "T"
    },
    {
        "input": "wombat",
        "output": "W"
    },
    {
        "input": "date",
        "output": "S"
    },
    {
        "input": "cold",
        "output": "L"
    },
    {
        "input": "choose",
        "output": "A"
    },
    {
        "input": "about",
        "output": "O"
    },
    {
        "input": "him",
        "output": "C"
    },
    {
        "input": "listen",
        "output": "A"
    },
    {
        "input": "camera",
        "output": "S"
    },
    {
        "input": "mirthful",
        "output": "J"
    },
    {
        "input": "blackberry",
        "output": "C"
    },
    {
        "input": "produce",
        "output": "O"
    },
    {
        "input": "narwhal",
        "output": "V"
    },
    {
        "input": "maximize",
        "output": "O"
    },
    {
        "input": "sofa",
        "output": "S"
    },
    {
        "input": "behind",
        "output": "C"
    },
    {
        "input": "friendly",
        "output": "S"
    },
    {
        "input": "value",
        "output": "B"
    },
    {
        "input": "sour",
        "output": "W"
    },
    {
        "input": "at",
        "output": "H"
    },
    {
        "input": "eagle",
        "output": "E"
    },
    {
        "input": "stapler",
        "output": "M"
    },
    {
        "input": "old",
        "output": "D"
    },
    {
        "input": "transform",
        "output": "Y"
    },
    {
        "input": "fear",
        "output": "B"
    },
    {
        "input": "cry",
        "output": "A"
    },
    {
        "input": "caribou",
        "output": "L"
    },
    {
        "input": "blanket",
        "output": "T"
    },
    {
        "input": "blue",
        "output": "M"
    },
    {
        "input": "tenacious",
        "output": "J"
    },
    {
        "input": "pig",
        "output": "P"
    },
    {
        "input": "kayak",
        "output": "P"
    },
    {
        "input": "keep",
        "output": "D"
    },
    {
        "input": "compete",
        "output": "H"
    },
    {
        "input": "organize",
        "output": "F"
    },
    {
        "input": "quick-witted",
        "output": "P"
    },
    {
        "input": "they",
        "output": "W"
    },
    {
        "input": "tiger",
        "output": "D"
    },
    {
        "input": "cowardly",
        "output": "D"
    },
    {
        "input": "rabbit",
        "output": "F"
    },
    {
        "input": "jacket",
        "output": "O"
    },
    {
        "input": "persimmon",
        "output": "R"
    },
    {
        "input": "phone",
        "output": "F"
    },
    {
        "input": "negotiate",
        "output": "N"
    },
    {
        "input": "dove",
        "output": "P"
    },
    {
        "input": "chimpanzee",
        "output": "F"
    },
    {
        "input": "fearless",
        "output": "G"
    },
    {
        "input": "dazzling",
        "output": "O"
    },
    {
        "input": "yacht",
        "output": "P"
    },
    {
        "input": "juice",
        "output": "T"
    },
    {
        "input": "kind",
        "output": "P"
    },
    {
        "input": "shirt",
        "output": "C"
    },
    {
        "input": "thoughtful",
        "output": "I"
    },
    {
        "input": "cockroach",
        "output": "M"
    },
    {
        "input": "paint",
        "output": "I"
    },
    {
        "input": "grape",
        "output": "M"
    },
    {
        "input": "peach",
        "output": "C"
    },
    {
        "input": "energetic",
        "output": "K"
    },
    {
        "input": "myself",
        "output": "C"
    },
    {
        "input": "to",
        "output": "H"
    },
    {
        "input": "clementine",
        "output": "L"
    },
    {
        "input": "ecstatic",
        "output": "C"
    },
    {
        "input": "generous",
        "output": "M"
    },
    {
        "input": "crow",
        "output": "T"
    },
    {
        "input": "approve",
        "output": "T"
    },
    {
        "input": "dynamic",
        "output": "M"
    },
    {
        "input": "whale",
        "output": "K"
    },
    {
        "input": "like",
        "output": "C"
    },
    {
        "input": "green",
        "output": "P"
    },
    {
        "input": "memorize",
        "output": "M"
    },
    {
        "input": "puma",
        "output": "V"
    },
    {
        "input": "reach",
        "output": "G"
    },
    {
        "input": "manipulate",
        "output": "T"
    },
    {
        "input": "plan",
        "output": "D"
    },
    {
        "input": "ostrich",
        "output": "V"
    },
    {
        "input": "towel",
        "output": "R"
    },
    {
        "input": "slow",
        "output": "E"
    },
    {
        "input": "before",
        "output": "F"
    },
    {
        "input": "bear",
        "output": "I"
    },
    {
        "input": "bottle",
        "output": "H"
    },
    {
        "input": "fan",
        "output": "O"
    },
    {
        "input": "badger",
        "output": "F"
    },
    {
        "input": "blissful",
        "output": "R"
    },
    {
        "input": "fresh",
        "output": "P"
    },
    {
        "input": "wet",
        "output": "I"
    },
    {
        "input": "juggle",
        "output": "K"
    },
    {
        "input": "maracas",
        "output": "C"
    },
    {
        "input": "net",
        "output": "F"
    },
    {
        "input": "mandarine",
        "output": "L"
    },
    {
        "input": "genuine",
        "output": "G"
    },
    {
        "input": "over",
        "output": "O"
    },
    {
        "input": "duck",
        "output": "M"
    },
    {
        "input": "firefly",
        "output": "T"
    },
    {
        "input": "nourish",
        "output": "A"
    },
    {
        "input": "sensible",
        "output": "P"
    },
    {
        "input": "relax",
        "output": "A"
    },
    {
        "input": "earring",
        "output": "G"
    },
    {
        "input": "okapi",
        "output": "L"
    },
    {
        "input": "laptop",
        "output": "J"
    },
    {
        "input": "examine",
        "output": "W"
    },
    {
        "input": "coral",
        "output": "L"
    },
    {
        "input": "plum",
        "output": "S"
    },
    {
        "input": "window",
        "output": "I"
    },
    {
        "input": "luminous",
        "output": "U"
    },
    {
        "input": "crocodile",
        "output": "M"
    },
    {
        "input": "develop",
        "output": "R"
    },
    {
        "input": "lovely",
        "output": "D"
    },
    {
        "input": "kill",
        "output": "S"
    },
    {
        "input": "cactus",
        "output": "R"
    },
    {
        "input": "coyote",
        "output": "M"
    },
    {
        "input": "open",
        "output": "F"
    },
    {
        "input": "collect",
        "output": "B"
    },
    {
        "input": "lynx",
        "output": "G"
    },
    {
        "input": "violet",
        "output": "W"
    },
    {
        "input": "vase",
        "output": "K"
    },
    {
        "input": "koala",
        "output": "P"
    },
    {
        "input": "fork",
        "output": "T"
    },
    {
        "input": "basket",
        "output": "B"
    },
    {
        "input": "walk",
        "output": "U"
    },
    {
        "input": "caterpillar",
        "output": "M"
    },
    {
        "input": "cream",
        "output": "E"
    },
    {
        "input": "skunk",
        "output": "M"
    },
    {
        "input": "pen",
        "output": "B"
    },
    {
        "input": "cheap",
        "output": "I"
    },
    {
        "input": "that",
        "output": "C"
    },
    {
        "input": "cake",
        "output": "N"
    },
    {
        "input": "hungry",
        "output": "P"
    },
    {
        "input": "label",
        "output": "C"
    },
    {
        "input": "mango",
        "output": "O"
    },
    {
        "input": "lucky",
        "output": "M"
    },
    {
        "input": "hate",
        "output": "Y"
    },
    {
        "input": "fig",
        "output": "B"
    },
    {
        "input": "huckleberry",
        "output": "C"
    },
    {
        "input": "moose",
        "output": "B"
    },
    {
        "input": "daring",
        "output": "T"
    },
    {
        "input": "fossa",
        "output": "E"
    },
    {
        "input": "bat",
        "output": "M"
    },
    {
        "input": "beneath",
        "output": "W"
    },
    {
        "input": "handle",
        "output": "H"
    },
    {
        "input": "kindle",
        "output": "K"
    },
    {
        "input": "reindeer",
        "output": "W"
    },
    {
        "input": "impala",
        "output": "G"
    },
    {
        "input": "gentle",
        "output": "R"
    },
    {
        "input": "earmuffs",
        "output": "C"
    },
    {
        "input": "television",
        "output": "A"
    },
    {
        "input": "map",
        "output": "J"
    },
    {
        "input": "naughty",
        "output": "R"
    },
    {
        "input": "smart",
        "output": "S"
    },
    {
        "input": "those",
        "output": "P"
    },
    {
        "input": "oryx",
        "output": "V"
    },
    {
        "input": "noble",
        "output": "T"
    },
    {
        "input": "orange",
        "output": "B"
    },
    {
        "input": "mild",
        "output": "P"
    },
    {
        "input": "cube",
        "output": "B"
    },
    {
        "input": "watermelon",
        "output": "O"
    },
    {
        "input": "discover",
        "output": "M"
    },
    {
        "input": "minimize",
        "output": "A"
    },
    {
        "input": "ant",
        "output": "W"
    },
    {
        "input": "scorpion",
        "output": "B"
    },
    {
        "input": "soft",
        "output": "W"
    },
    {
        "input": "obtain",
        "output": "C"
    },
    {
        "input": "on",
        "output": "M"
    },
    {
        "input": "cookie",
        "output": "W"
    },
    {
        "input": "mantis",
        "output": "W"
    },
    {
        "input": "work",
        "output": "P"
    },
    {
        "input": "prepare",
        "output": "V"
    },
    {
        "input": "wallet",
        "output": "D"
    },
    {
        "input": "cougar",
        "output": "O"
    },
    {
        "input": "toucan",
        "output": "O"
    },
    {
        "input": "zucchini",
        "output": "P"
    },
    {
        "input": "snorkel",
        "output": "F"
    },
    {
        "input": "affectionate",
        "output": "S"
    },
    {
        "input": "magnificent",
        "output": "A"
    },
    {
        "input": "celebrate",
        "output": "P"
    },
    {
        "input": "strong",
        "output": "D"
    },
    {
        "input": "beyond",
        "output": "S"
    },
    {
        "input": "concerning",
        "output": "C"
    },
    {
        "input": "swan",
        "output": "R"
    },
    {
        "input": "pork",
        "output": "Q"
    },
    {
        "input": "giraffe",
        "output": "H"
    },
    {
        "input": "cobra",
        "output": "S"
    },
    {
        "input": "exuberant",
        "output": "O"
    },
    {
        "input": "throughout",
        "output": "F"
    },
    {
        "input": "silver",
        "output": "S"
    },
    {
        "input": "until",
        "output": "B"
    },
    {
        "input": "yellow",
        "output": "G"
    },
    {
        "input": "gracious",
        "output": "C"
    },
    {
        "input": "recruit",
        "output": "S"
    },
    {
        "input": "explore",
        "output": "C"
    }
]